{"sections":{"heading":{"type":"pages_heading","blocks":{"89b1a94e-2cf5-4075-a6af-0969fbaeae2c":{"type":"1","settings":{"color":"#fff"}}},"block_order":["89b1a94e-2cf5-4075-a6af-0969fbaeae2c"],"settings":{"image":"shopify:\/\/shop_images\/Walkway_76798899-6dcb-4fad-8d5a-b9195380a751.jpg","parallax":false,"color":"#000","overlay":35,"padding":50,"paddingmb":50,"bg_pos":"center center","bg_repeat":"no-repeat","bg_size":"cover","bg_att":"scroll"}},"main":{"type":"main-page","settings":{}}},"order":["heading","main"]}